wrapper/__init__.py
wrapper/alicebluepy.py
ant_pya3-2.0.9.dist-info/METADATA
ant_pya3-2.0.9.dist-info/WHEEL
ant_pya3-2.0.9.dist-info/top_level.txt
ant_pya3-2.0.9.dist-info/RECORD
