Metadata-Version: 2.4
Name: ant-pya3
Version: 2.0.9
Summary: Official Python SDK for Alice Blue API
Home-page: https://a3.aliceblueonline.com/
Author: Codifi
Author-email: pradeep@codifi.in
License: MIT
Classifier: Programming Language :: Python :: 3.8
Classifier: License :: OSI Approved :: MIT License
Classifier: Operating System :: OS Independent
Classifier: Natural Language :: English
Classifier: Intended Audience :: Developers
Requires-Python: >=3.7
Requires-Dist: requests
Requires-Dist: pandas
Requires-Dist: websocket-client
Requires-Dist: rel
Dynamic: author
Dynamic: author-email
Dynamic: classifier
Dynamic: description
Dynamic: description-content-type
Dynamic: home-page
Dynamic: license
Dynamic: requires-dist
Dynamic: requires-python
Dynamic: summary
